<keymap version="1" name="mux" parent="Default for GNOME">
  <action id="ActivateTerminalToolWindow">
    <keyboard-shortcut first-keystroke="alt f12" />
    <keyboard-shortcut first-keystroke="ctrl back_quote" />
  </action>
  <action id="Arrangement.Alias.Rule.Edit" />
  <action id="Arrangement.Rule.Edit" />
  <action id="ChangesView.Rename">
    <keyboard-shortcut first-keystroke="shift f6" />
  </action>
  <action id="ChooseDebugConfiguration">
    <keyboard-shortcut first-keystroke="shift alt f9" />
    <keyboard-shortcut first-keystroke="f5" />
  </action>
  <action id="ChooseRunConfiguration">
    <keyboard-shortcut first-keystroke="shift alt f10" />
    <keyboard-shortcut first-keystroke="ctrl f5" />
  </action>
  <action id="CloseContent">
    <keyboard-shortcut first-keystroke="ctrl f4" />
    <keyboard-shortcut first-keystroke="ctrl w" />
  </action>
  <action id="CopyElement" />
  <action id="Debugger.EditArrayFilter" />
  <action id="Debugger.EditCustomField" />
  <action id="DuplicatesForm.SendToLeft" />
  <action id="DuplicatesForm.SendToRight" />
  <action id="EditorCodeBlockEndWithSelection" />
  <action id="EditorCodeBlockStartWithSelection" />
  <action id="EditorSelectWord" />
  <action id="FileChooser.GotoHome" />
  <action id="FileChooser.GotoProject" />
  <action id="Git.Reword.Commit">
    <keyboard-shortcut first-keystroke="shift f6" />
  </action>
  <action id="GotoBookmark1" />
  <action id="GotoBookmark2" />
  <action id="GotoNextError" />
  <action id="GuiDesigner.CreateListener" />
  <action id="GuiDesigner.EditComponent" />
  <action id="GuiDesigner.EditGroup" />
  <action id="MethodHierarchy.OverrideMethodAction" />
  <action id="NextSplitter">
    <keyboard-shortcut first-keystroke="ctrl 2" />
  </action>
  <action id="OpenFile">
    <keyboard-shortcut first-keystroke="ctrl o" />
  </action>
  <action id="OverrideMethods" />
  <action id="PrevSplitter">
    <keyboard-shortcut first-keystroke="ctrl 1" />
  </action>
  <action id="QuickChangeScheme" />
  <action id="Refresh" />
  <action id="RenameElement">
    <keyboard-shortcut first-keystroke="shift f6" />
    <keyboard-shortcut first-keystroke="f2" />
  </action>
  <action id="Rerun" />
  <action id="ShelvedChanges.Rename">
    <keyboard-shortcut first-keystroke="shift f6" />
  </action>
  <action id="SplitVertically">
    <keyboard-shortcut first-keystroke="ctrl back_slash" />
  </action>
  <action id="Terminal.MoveToolWindowTabLeft">
    <keyboard-shortcut first-keystroke="shift ctrl alt left" />
    <keyboard-shortcut first-keystroke="shift ctrl open_bracket" />
  </action>
  <action id="Terminal.MoveToolWindowTabRight">
    <keyboard-shortcut first-keystroke="shift ctrl alt right" />
    <keyboard-shortcut first-keystroke="shift ctrl close_bracket" />
  </action>
  <action id="Vcs.Log.Refresh" />
  <action id="XDebugger.EditWatch" />
  <action id="XDebugger.SetValue" />
  <action id="hg4idea.QRefresh" />
</keymap>
